array_to_latex/__init__.py
array_to_latex-0.92.dist-info/METADATA
array_to_latex-0.92.dist-info/WHEEL
array_to_latex-0.92.dist-info/top_level.txt
array_to_latex-0.92.dist-info/RECORD
