Metadata-Version: 2.1
Name: array_to_latex
Version: 0.92
Summary: Return Numpy and Pandas arrays as formatted LaTeX arrays.
Home-page: https://github.com/josephcslater/array_to_latex/
Author: Joseph C. Slater
Author-email: joseph.c.slater@gmail.com
Keywords: latex,array,format,numpy,scipy
Classifier: Development Status :: 5 - Production/Stable
Classifier: Intended Audience :: Science/Research
Classifier: License :: OSI Approved :: MIT License
Classifier: Environment :: Console
Classifier: Intended Audience :: End Users/Desktop
Classifier: Intended Audience :: Education
Classifier: Intended Audience :: Science/Research
Classifier: Programming Language :: Python
Classifier: Programming Language :: Python :: 3.4
Classifier: Programming Language :: Python :: 3.5
Classifier: Programming Language :: Python :: 3.6
Classifier: Topic :: Scientific/Engineering
Classifier: Topic :: Text Processing :: Markup :: LaTeX
Classifier: Operating System :: Microsoft :: Windows
Classifier: Operating System :: POSIX
Classifier: Operating System :: Unix
Classifier: Operating System :: MacOS
Classifier: Topic :: Utilities
Requires-Dist: numpy
Requires-Dist: pandas
Requires-Dist: clipboard
